{
  "course_sections": [
    {
      "staff_name": "REYES, A.L.",
      "section_id": "UCLA_AERO_ST_AERO_ST_1A_LEC_1",
      "school_id": 1,
      "section_name": "LEC 1",
      "course_id": "UCLA_AERO_ST_AERO_ST_1A",
      "events": [
        {
          "status": "Open",
          "event_type": "LEC 1",
          "school_specific_event_id": "102048200",
          "event_id": "UCLA_AERO_ST_AERO_ST_1A_LEC_1_102048200",
          "times_and_locations": [
            {
              "timeInterval": "12:00P - 1:50P",
              "weekdays": "FRI",
              "location": "HAINES A18"
            }
          ],
          "section_id": "UCLA_AERO_ST_AERO_ST_1A_LEC_1",
          "enrollment_cap": 20,
          "number_waitlisted": 0,
          "number_enrolled": 14,
          "waitlist_capacity": 0,
          "school_id": 1
        }
      ]
    },
    {
      "staff_name": "REYES, A.L.",
      "section_id": "UCLA_AERO_ST_AERO_ST_1A_LEC_2",
      "school_id": 1,
      "section_name": "LEC 2",
      "course_id": "UCLA_AERO_ST_AERO_ST_1A",
      "events": [
        {
          "status": "W-List",
          "event_type": "LEC 2",
          "school_specific_event_id": "102048201",
          "event_id": "UCLA_AERO_ST_AERO_ST_1A_LEC_2_102048201",
          "times_and_locations": [
            {
              "timeInterval": "9:00A - 9:50A",
              "weekdays": "TUE",
              "location": "KAUFMAN 101"
            }
          ],
          "section_id": "UCLA_AERO_ST_AERO_ST_1A_LEC_2",
          "enrollment_cap": 20,
          "number_waitlisted": 0,
          "number_enrolled": 2,
          "waitlist_capacity": 0,
          "school_id": 1
        }
      ]
    },
    {
      "staff_name": "",
      "section_id": "UCLA_AERO_ST_AERO_ST_1A_LEC_3",
      "school_id": 1,
      "section_name": "LEC 3",
      "course_id": "UCLA_AERO_ST_AERO_ST_1A",
      "events": [
        {
          "status": "Cancelled",
          "event_type": "LEC 3",
          "school_specific_event_id": "102048203",
          "event_id": "UCLA_AERO_ST_AERO_ST_1A_LEC_3_102048203",
          "times_and_locations": [
            {
              "timeInterval": "1:00P - 1:50P",
              "weekdays": "FRI",
              "location": "HAINES "
            }
          ],
          "section_id": "UCLA_AERO_ST_AERO_ST_1A_LEC_3",
          "enrollment_cap": 0,
          "number_waitlisted": 0,
          "number_enrolled": 0,
          "waitlist_capacity": 0,
          "school_id": 1
        }
      ]
    },
    {
      "staff_name": "PALSBERG, J.",
      "section_id": "UCLA_COM_SCI_COM_SCI_1_SEM_1",
      "school_id": 1,
      "section_name": "SEM 1",
      "course_id": "UCLA_COM_SCI_COM_SCI_1",
      "events": [
        {
          "status": "Open",
          "event_type": "SEM 1",
          "school_specific_event_id": "187003200",
          "event_id": "UCLA_COM_SCI_COM_SCI_1_SEM_1_187003200",
          "times_and_locations": [
            {
              "timeInterval": "1:00P - 1:50P",
              "weekdays": "MON",
              "location": "HAINES 118"
            }
          ],
          "section_id": "UCLA_COM_SCI_COM_SCI_1_SEM_1",
          "enrollment_cap": 140,
          "number_waitlisted": 0,
          "number_enrolled": 138,
          "waitlist_capacity": 4,
          "school_id": 1
        },
        {
          "status": "Open",
          "event_type": "DIS 1A",
          "school_specific_event_id": "187003201",
          "event_id": "UCLA_COM_SCI_COM_SCI_1_SEM_1_187003201",
          "times_and_locations": [
            {
              "timeInterval": "1:00P - 1:50P",
              "weekdays": "FRI",
              "location": "FRANZ 1260"
            }
          ],
          "section_id": "UCLA_COM_SCI_COM_SCI_1_SEM_1",
          "enrollment_cap": 79,
          "number_waitlisted": 0,
          "number_enrolled": 77,
          "waitlist_capacity": 4,
          "school_id": 1
        },
        {
          "status": "Closed",
          "event_type": "DIS 1B",
          "school_specific_event_id": "187003202",
          "event_id": "UCLA_COM_SCI_COM_SCI_1_SEM_1_187003202",
          "times_and_locations": [
            {
              "timeInterval": "1:00P - 1:50P",
              "weekdays": "WED",
              "location": "BOTANY 325"
            }
          ],
          "section_id": "UCLA_COM_SCI_COM_SCI_1_SEM_1",
          "enrollment_cap": 61,
          "number_waitlisted": 0,
          "number_enrolled": 61,
          "waitlist_capacity": 0,
          "school_id": 1
        }
      ]
    },
    {
      "staff_name": "EGGERT, P.R.",
      "section_id": "UCLA_COM_SCI_COM_SCI_130_LEC_1",
      "school_id": 1,
      "section_name": "LEC 1",
      "course_id": "UCLA_COM_SCI_COM_SCI_130",
      "events": [
        {
          "status": "Open",
          "event_type": "LEC 1",
          "school_specific_event_id": "187500200",
          "event_id": "UCLA_COM_SCI_COM_SCI_130_LEC_1_187500200",
          "times_and_locations": [
            {
              "timeInterval": "10:00A - 11:50A",
              "weekdays": "TUE",
              "location": "BOELTER 2444"
            },
            {
              "timeInterval": "10:00A - 11:50A",
              "weekdays": "THU",
              "location": "BOELTER 2444"
            },
            {
              "timeInterval": "10:00A - 11:50A",
              "weekdays": "TUE",
              "location": "BOELTER 2444"
            },
            {
              "timeInterval": "10:00A - 11:50A",
              "weekdays": "THU",
              "location": "BOELTER 2444"
            },
            {
              "timeInterval": "10:00A - 11:50A",
              "weekdays": "TUE",
              "location": "BOELTER 2444"
            },
            {
              "timeInterval": "10:00A - 11:50A",
              "weekdays": "THU",
              "location": "BOELTER 2444"
            },
            {
              "timeInterval": "10:00A - 11:50A",
              "weekdays": "TUE",
              "location": "BOELTER 2444"
            },
            {
              "timeInterval": "10:00A - 11:50A",
              "weekdays": "THU",
              "location": "BOELTER 2444"
            }
          ],
          "section_id": "UCLA_COM_SCI_COM_SCI_130_LEC_1",
          "enrollment_cap": 80,
          "number_waitlisted": 0,
          "number_enrolled": 78,
          "waitlist_capacity": 0,
          "school_id": 1
        },
        {
          "status": "Open",
          "event_type": "LAB 1A",
          "school_specific_event_id": "187500201",
          "event_id": "UCLA_COM_SCI_COM_SCI_130_LEC_1_187500201",
          "times_and_locations": [
            {
              "timeInterval": "2:00P - 3:50P",
              "weekdays": "FRI",
              "location": "BOELTER 5436"
            }
          ],
          "section_id": "UCLA_COM_SCI_COM_SCI_130_LEC_1",
          "enrollment_cap": 40,
          "number_waitlisted": 0,
          "number_enrolled": 39,
          "waitlist_capacity": 0,
          "school_id": 1
        },
        {
          "status": "Open",
          "event_type": "LAB 1B",
          "school_specific_event_id": "187500202",
          "event_id": "UCLA_COM_SCI_COM_SCI_130_LEC_1_187500202",
          "times_and_locations": [
            {
              "timeInterval": "12:00P - 1:50P",
              "weekdays": "FRI",
              "location": "BOELTER 5436"
            }
          ],
          "section_id": "UCLA_COM_SCI_COM_SCI_130_LEC_1",
          "enrollment_cap": 40,
          "number_waitlisted": 0,
          "number_enrolled": 39,
          "waitlist_capacity": 0,
          "school_id": 1
        }
      ]
    },
    {
      "staff_name": "Bo Mou",
      "section_id": "SJSU_ASIA_ASIA_104_LEC_01",
      "school_id": 2,
      "section_name": "LEC 01",
      "course_id": "SJSU_ASIA_ASIA_104",
      "events": [
        {
          "status": "Open",
          "event_type": "LEC 01",
          "school_specific_event_id": "10116",
          "event_id": "SJSU_ASIA_ASIA_104_LEC_01_10116",
          "times_and_locations": [],
          "section_id": "SJSU_ASIA_ASIA_104_LEC_01",
          "enrollment_cap": 40,
          "number_waitlisted": 0,
          "number_enrolled": 37,
          "waitlist_capacity": 100,
          "school_id": 2
        }
      ]
    }
  ]
}